Workbook

Sheet Assumptions
A1: AWDS MetroLink — Construction Stage Resourcing, FTE & Cost Model
A2: Assumptions & basis of estimate. Edit the gold cells on the 'Rates' tab — all sheets and the total cost update automatically.
A5: KEY ASSUMPTIONS
A6: Construction-stage durations
A7: • Management team | C7: 36 months
A8: • Contract Managers (and their delivery team) | C8: 18 months
A9: • Support staff | C9: 18 months
A10: • Designers (reachback) | C10: 18 months
A11: Number of contract packages / Contract Managers | C11: 16 (one per package — see note 1)
A12: Rates & hours | C12: See the 'Rates' tab (editable).
A14: DEFINITIONS
A15: FTE | C15: 1.0 FTE = one full-time-equivalent person at 100% utilisation.
A16: Utilisation % | C16: Share of a person's time spent on AWDS construction-stage work.
A17: FTE (modelled) | C17: =Headcount × Utilisation %
A18: Effort (person-months) | C18: =FTE × Duration (months)
A19: Effort (person-years) | C19: =Person-months ÷ 12
A20: Cost (€) | C20: =Person-months × Hours-per-month × Rate (from 'Rates' tab)
A22: FTE vs NON-FTE TREATMENT
A23: Management team & Contract Managers | C23: Dedicated FTE — charged at the Management rate.
A24: Support staff | C24: Shared / part-time — charged at the Support rate.
A25: Designers | C25: Reachback / part-time — charged at the Designer rate.
A27: SCOPE CONTEXT (drives the team make-up)
A28: At construction stage the Contract Managers and their teams are NOT site supervision. Their remit is:
A29: • Raising / tracking / closing RFIs
A30: • Reviewing contractor design proposals
A31: • Progress, design and coordination meetings; occasional site visits
A32: • Meetings with utility asset owners
A33: • Updating and managing the as-built drawings / CDE
A34: • NEC contract administration, change and reporting
A36: NOTES
A37: 1. Contract Manager headcount is taken from the management org chart (16). In practice some packages are
A38: combined under a single Contract Manager (e.g. M140 & M146), so the dedicated CM count may be lower —
A39: edit the headcount on sheet 1 to suit.
... A41: 3. Management team excludes the Procurement Lead (procurement complete by construction stage).

Sheet Rates
A1: Rates & Cost Inputs
A2: Edit the gold cells below. Every sheet and the total cost recalculate automatically.
A5: Hours per person-month | C5: 160 | D5: Working hours used to convert person-months to chargeable hours
A6: Management rate (€/hr) | C6: 110 | D6: Applies to the Management Team and Contract Managers (FTE)
A7: Support staff rate (€/hr) | C7: 50 | D7: Applies to all Support Staff (interface, back-office & contract delivery support)
A8: Designer rate (€/hr) | C8: 95 | D8: Applies to the Designers (reachback) team
A11: Indicative total construction-stage cost (€) | C11: ='Summary'!$H$10
A12: (labour only — see Assumptions)

Sheet Summary
A1: Construction Stage — Resource & Cost Summary
A2: Roll-up of all categories. Cost is driven by the editable 'Rates' tab.
A4: Category | B4: Type | C4: Headcount | D4: FTE (modelled) | E4: Duration (months) | F4: Effort (person-months) | G4: Effort (person-years) | H4: Cost (€)
A5: Management Team | B5: FTE (dedicated) | C5: ='1 · Mgmt & Contract Mgrs'!B14 | D5: ='1 · Mgmt & Contract Mgrs'!D14 | E5: 36 | F5: ='1 · Mgmt & Contract Mgrs'!F14 | G5: ='1 · Mgmt & Contract Mgrs'!G14 | H5: ='1 · Mgmt & Contract Mgrs'!H14
A6: Contract Managers | B6: FTE (dedicated) | C6: ='1 · Mgmt & Contract Mgrs'!B18 | D6: ='1 · Mgmt & Contract Mgrs'!D18 | E6: 18 | F6: ='1 · Mgmt & Contract Mgrs'!F18 | G6: ='1 · Mgmt & Contract Mgrs'!G18 | H6: ='1 · Mgmt & Contract Mgrs'!H18
A7: Contract Delivery Support | B7: Utilisation | C7: ='2 · Support Staff'!B12 | D7: ='2 · Support Staff'!D12 | E7: 18 | F7: ='2 · Support Staff'!F12 | G7: ='2 · Support Staff'!G12 | H7: ='2 · Support Staff'!H12
A8: Project Support (Interface & Back-Office) | B8: Utilisation | C8: ='2 · Support Staff'!B36 | D8: ='2 · Support Staff'!D36 | E8: 18 | F8: ='2 · Support Staff'!F36 | G8: ='2 · Support Staff'!G36 | H8: ='2 · Support Staff'!H36
A9: Designers (reachback) | B9: Utilisation | C9: ='3 · Designers'!B16 | D9: ='3 · Designers'!D16 | E9: 18 | F9: ='3 · Designers'!F16 | G9: ='3 · Designers'!G16 | H9: ='3 · Designers'!H16
A10: TOTAL — Construction Stage | C10: =SUM(C5:C9) | D10: =SUM(D5:D9) | F10: =SUM(F5:F9) | G10: =SUM(G5:G9) | H10: =SUM(H5:H9)
A12: FTE (Management + Contract Managers) | D12: =D5+D6
A13: FTE-equivalent (Support + Designers) | D13: =D7+D8+D9

Sheet 1 · Mgmt & Contract Mgrs
A1: 1 · Management Team & Contract Managers — FTE
A2: Dedicated full-time-equivalent resource. Charged at the Management rate (Rates tab).
A4: Role | B4: Headcount | C4: Utilisation % | D4: FTE | E4: Duration (months) | F4: Effort (person-months) | G4: Effort (person-years) | H4: Cost (€) | I4: Basis / notes
A5: MANAGEMENT TEAM (36 months)
A6: AWDS Project Director | B6: 1 | C6: 0.25 | D6: =B6*C6 | E6: 36 | F6: =D6*E6 | G6: =F6/12 | H6: =F6*'Rates'!$C$5*'Rates'!$C$6 | I6: Part-time senior oversight & governance
A7: AWDS Project Management Lead | B7: 1 | C7: 1 | D7: =B7*C7 | E7: 36 | F7: =D7*E7 | G7: =F7/12 | H7: =F7*'Rates'!$C$5*'Rates'!$C$6 | I7: Full-time; leads delivery across all packages
A8: AWDS Deputy Project Manager | B8: 1 | C8: 1 | D8: =B8*C8 | E8: 36 | F8: =D8*E8 | G8: =F8/12 | H8: =F8*'Rates'!$C$5*'Rates'!$C$6 | I8: Full-time; daily operations & coordination
A9: AWDS Design Management Lead | B9: 1 | C9: 1 | D9: =B9*C9 | E9: 36 | F9: =D9*E9 | G9: =F9/12 | H9: =F9*'Rates'!$C$5*'Rates'!$C$6 | I9: Full-time; design integration & reachback mgmt
A10: AWDS PMO Lead | B10: 1 | C10: 1 | D10: =B10*C10 | E10: 36 | F10: =D10*E10 | G10: =F10/12 | H10: =F10*'Rates'!$C$5*'Rates'!$C$6 | I10: Full-time; controls, reporting, information mgmt
A11: AWDS Technical Delivery Lead | B11: 1 | C11: 1 | D11: =B11*C11 | E11: 36 | F11: =D11*E11 | G11: =F11/12 | H11: =F11*'Rates'!$C$5*'Rates'!$C$6 | I11: Full-time; technical assurance & verification
A12: AWDS Commercial Lead | B12: 1 | C12: 1 | D12: =B12*C12 | E12: 36 | F12: =D12*E12 | G12: =F12/12 | H12: =F12*'Rates'!$C$5*'Rates'!$C$6 | I12: Full-time; NEC commercial & change
A13: AWDS Cost Management Lead | B13: 1 | C13: 1 | D13: =B13*C13 | E13: 36 | F13: =D13*E13 | G13: =F13/12 | H13: =F13*'Rates'!$C$5*'Rates'!$C$6 | I13: Full-time; cost control & forecasting
A14: Subtotal — MANAGEMENT TEAM (36 months) | B14: =SUM(B6:B13) | D14: =SUM(D6:D13) | F14: =SUM(F6:F13) | G14: =SUM(G6:G13) | H14: =SUM(H6:H13)
A16: CONTRACT MANAGERS (18 months)
A17: AWDS Contract Manager (one per package) | B17: 16 | C17: 1 | D17: =B17*C17 | E17: 18 | F17: =D17*E17 | G17: =F17/12 | H17: =F17*'Rates'!$C$5*'Rates'!$C$6 | I17: Package PM: RFIs, contractor & utility-owner meetings, design-proposal review, as-builts, NEC admin
A18: Subtotal — CONTRACT MANAGERS (18 months) | B18: =SUM(B17:B17) | D18: =SUM(D17:D17) | F18: =SUM(F17:F17) | G18: =SUM(G17:G17) | H18: =SUM(H17:H17)
A20: TOTAL | B20: =B14+B18 | D20: =D14+D18 | F20: =F14+F18 | G20: =G14+G18 | H20: =H14+H18

Sheet 2 · Support Staff
A1: 2 · Support Staff — utilisation-based (non-FTE)
A2: Shared / part-time resources. Charged at the Support rate (Rates tab).
A4: Role | B4: Headcount | C4: Utilisation % | D4: FTE | E4: Duration (months) | F4: Effort (person-months) | G4: Effort (person-years) | H4: Cost (€) | I4: Basis / notes
A5: CONTRACT DELIVERY SUPPORT (team around the Contract Managers, 18 months)
A6: Contracts / Technical Engineer | B6: 8 | C6: 0.75 | D6: =B6*C6 | E6: 18 | F6: =D6*E6 | G6: =F6/12 | H6: =F6*'Rates'!$C$5*'Rates'!$C$7 | I6: Reviews contractor design proposals, raises/closes RFIs, technical correspondence (~1 per 2 packages)
A7: Document Controller / As-Built Coordinator | B7: 4 | C7: 0.6 | D7: =B7*C7 | E7: 18 | F7: =D7*E7 | G7: =F7/12 | H7: =F7*'Rates'!$C$5*'Rates'!$C$7 | I7: Manages & updates as-built drawings and CDE (~1 per 4 packages)
A8: Quantity Surveyor / Commercial Support | B8: 4 | C8: 0.6 | D8: =B8*C8 | E8: 18 | F8: =D8*E8 | G8: =F8/12 | H8: =F8*'Rates'!$C$5*'Rates'!$C$7 | I8: NEC change, valuations and payment support (~1 per 4 packages)
A9: Utilities Liaison Coordinator | B9: 2 | C9: 0.5 | D9: =B9*C9 | E9: 18 | F9: =D9*E9 | G9: =F9/12 | H9: =F9*'Rates'!$C$5*'Rates'!$C$7 | I9: Meetings & coordination with utility asset owners
A10: CEMP / Environmental Coordinator | B10: 2 | C10: 0.4 | D10: =B10*C10 | E10: 18 | F10: =D10*E10 | G10: =F10/12 | H10: =F10*'Rates'!$C$5*'Rates'!$C$7 | I10: Environmental compliance and CEMP across packages
A11: Planner / Scheduler (package) | B11: 2 | C11: 0.5 | D11: =B11*C11 | E11: 18 | F11: =D11*E11 | G11: =F11/12 | H11: =F11*'Rates'!$C$5*'Rates'!$C$7 | I11: Programme tracking at package level
A12: Subtotal — CONTRACT DELIVERY SUPPORT (team around the Contract Managers, 18 months) | B12: =SUM(B6:B11) | D12: =SUM(D6:D11) | F12: =SUM(F6:F11) | G12: =SUM(G6:G11) | H12: =SUM(H6:H11)
A14: PROJECT SUPPORT — Interface & Back-Office (18 months)
A15: BIM Manager | B15: 1 | C15: 0.5 | D15: =B15*C15 | E15: 18 | F15: =D15*E15 | G15: =F15/12 | H15: =F15*'Rates'!$C$5*'Rates'!$C$7 | I15: Shared across programme
A16: Deputy BIM Manager | B16: 1 | C16: 0.5 | D16: =B16*C16 | E16: 18 | F16: =D16*E16 | G16: =F16/12 | H16: =F16*'Rates'!$C$5*'Rates'!$C$7
A17: Information Manager | B17: 1 | C17: 0.5 | D17: =B17*C17 | E17: 18 | F17: =D17*E17 | G17: =F17/12 | H17: =F17*'Rates'!$C$5*'Rates'!$C$7
A18: Deputy Information Manager | B18: 1 | C18: 0.4 | D18: =B18*C18 | E18: 18 | F18: =D18*E18 | G18: =F18/12 | H18: =F18*'Rates'!$C$5*'Rates'!$C$7
A19: Senior GIS Consultant | B19: 1 | C19: 0.3 | D19: =B19*C19 | E19: 18 | F19: =D19*E19 | G19: =F19/12 | H19: =F19*'Rates'!$C$5*'Rates'!$C$7 | I19: On-demand
A20: Senior GIS Analyst | B20: 1 | C20: 0.4 | D20: =B20*C20 | E20: 18 | F20: =D20*E20 | G20: =F20/12 | H20: =F20*'Rates'!$C$5*'Rates'!$C$7
A21: Surveys Coordinator | B21: 1 | C21: 0.3 | D21: =B21*C21 | E21: 18 | F21: =D21*E21 | G21: =F21/12 | H21: =F21*'Rates'!$C$5*'Rates'!$C$7 | I21: Ad-hoc survey requests
A22: CDE Document Controller (project) | B22: 1 | C22: 0.7 | D22: =B22*C22 | E22: 18 | F22: =D22*E22 | G22: =F22/12 | H22: =F22*'Rates'!$C$5*'Rates'!$C$7 | I22: Project-wide CDE
A23: BusConnects Interface | B23: 1 | C23: 0.2 | D23: =B23*C23 | E23: 18 | F23: =D23*E23 | G23: =F23/12 | H23: =F23*'Rates'!$C$5*'Rates'!$C$7 | I23: Interface management
A24: DAA Interface | B24: 1 | C24: 0.2 | D24: =B24*C24 | E24: 18 | F24: =D24*E24 | G24: =F24/12 | H24: =F24*'Rates'!$C$5*'Rates'!$C$7 | I24: Interface management
A25: UAO Engagement Team | B25: 2 | C25: 0.3 | D25: =B25*C25 | E25: 18 | F25: =D25*E25 | G25: =F25/12 | H25: =F25*'Rates'!$C$5*'Rates'!$C$7 | I25: Utility/asset-owner engagement
A26: Administrator | B26: 2 | C26: 0.8 | D26: =B26*C26 | E26: 18 | F26: =D26*E26 | G26: =F26/12 | H26: =F26*'Rates'!$C$5*'Rates'!$C$7 | I26: Team & document admin
A27: Health & Safety Advisor | B27: 1 | C27: 0.5 | D27: =B27*C27 | E27: 18 | F27: =D27*E27 | G27: =F27/12 | H27: =F27*'Rates'!$C$5*'Rates'!$C$7 | I27: CDM / safety in design support
A28: QA / QC Manager | B28: 1 | C28: 0.5 | D28: =B28*C28 | E28: 18 | F28: =D28*E28 | G28: =F28/12 | H28: =F28*'Rates'!$C$5*'Rates'!$C$7 | I28: Quality assurance
A29: Risk Manager | B29: 1 | C29: 0.3 | D29: =B29*C29 | E29: 18 | F29: =D29*E29 | G29: =F29/12 | H29: =F29*'Rates'!$C$5*'Rates'!$C$7
A30: Project Controls Analyst | B30: 1 | C30: 0.6 | D30: =B30*C30 | E30: 18 | F30: =D30*E30 | G30: =F30/12 | H30: =F30*'Rates'!$C$5*'Rates'!$C$7 | I30: Reporting & dashboards
A31: HR & People Coordinator | B31: 1 | C31: 0.25 | D31: =B31*C31 | E31: 18 | F31: =D31*E31 | G31: =F31/12 | H31: =F31*'Rates'!$C$5*'Rates'!$C$7
A32: IT / Systems Support | B32: 1 | C32: 0.25 | D32: =B32*C32 | E32: 18 | F32: =D32*E32 | G32: =F32/12 | H32: =F32*'Rates'!$C$5*'Rates'!$C$7
A33: Communications & Stakeholder Liaison | B33: 1 | C33: 0.3 | D33: =B33*C33 | E33: 18 | F33: =D33*E33 | G33: =F33/12 | H33: =F33*'Rates'!$C$5*'Rates'!$C$7
A34: Training & Competency Coordinator | B34: 1 | C34: 0.2 | D34: =B34*C34 | E34: 18 | F34: =D34*E34 | G34: =F34/12 | H34: =F34*'Rates'!$C$5*'Rates'!$C$7
A35: Office Manager | B35: 1 | C35: 0.6 | D35: =B35*C35 | E35: 18 | F35: =D35*E35 | G35: =F35/12 | H35: =F35*'Rates'!$C$5*'Rates'!$C$7
A36: Subtotal — PROJECT SUPPORT — Interface & Back-Office (18 months) | B36: =SUM(B15:B35) | D36: =SUM(D15:D35) | F36: =SUM(F15:F35) | G36: =SUM(G15:G35) | H36: =SUM(H15:H35)
A38: TOTAL | B38: =B12+B36 | D38: =D12+D36 | F38: =F12+F36 | G38: =G12+G36 | H38: =H12+H36

Sheet 3 · Designers
A1: 3 · Designers — reachback, utilisation-based (non-FTE)
A2: Design discipline reachback team. Charged at the Designer rate (Rates tab).
A4: Role | B4: Headcount | C4: Utilisation % | D4: FTE | E4: Duration (months) | F4: Effort (person-months) | G4: Effort (person-years) | H4: Cost (€) | I4: Basis / notes
A5: DESIGN REACHBACK TEAM (18 months)
A6: Design Management / Coordination | B6: 1 | C6: 0.3 | D6: =B6*C6 | E6: 18 | F6: =D6*E6 | G6: =F6/12 | H6: =F6*'Rates'!$C$5*'Rates'!$C$8 | I6: Coordinates reachback requests
A7: Utilities South | B7: 3 | C7: 0.25 | D7: =B7*C7 | E7: 18 | F7: =D7*E7 | G7: =F7/12 | H7: =F7*'Rates'!$C$5*'Rates'!$C$8 | I7: Reachback — design queries & proposal review
A8: Sustainability | B8: 2 | C8: 0.15 | D8: =B8*C8 | E8: 18 | F8: =D8*E8 | G8: =F8/12 | H8: =F8*'Rates'!$C$5*'Rates'!$C$8 | I8: On-demand
A9: Land Access | B9: 2 | C9: 0.2 | D9: =B9*C9 | E9: 18 | F9: =D9*E9 | G9: =F9/12 | H9: =F9*'Rates'!$C$5*'Rates'!$C$8 | I9: On-demand
A10: Structures | B10: 2 | C10: 0.25 | D10: =B10*C10 | E10: 18 | F10: =D10*E10 | G10: =F10/12 | H10: =F10*'Rates'!$C$5*'Rates'!$C$8 | I10: Design review & RFI support
A11: Heritage | B11: 1 | C11: 0.1 | D11: =B11*C11 | E11: 18 | F11: =D11*E11 | G11: =F11/12 | H11: =F11*'Rates'!$C$5*'Rates'!$C$8 | I11: On-demand
A12: Cellars & Playing Pitches | B12: 1 | C12: 0.1 | D12: =B12*C12 | E12: 18 | F12: =D12*E12 | G12: =F12/12 | H12: =F12*'Rates'!$C$5*'Rates'!$C$8 | I12: On-demand
A13: Archaeology | B13: 1 | C13: 0.15 | D13: =B13*C13 | E13: 18 | F13: =D13*E13 | G13: =F13/12 | H13: =F13*'Rates'!$C$5*'Rates'!$C$8 | I13: On-demand
A14: Biodiversity | B14: 1 | C14: 0.1 | D14: =B14*C14 | E14: 18 | F14: =D14*E14 | G14: =F14/12 | H14: =F14*'Rates'!$C$5*'Rates'!$C$8 | I14: On-demand
A15: Env. Monitoring | B15: 2 | C15: 0.2 | D15: =B15*C15 | E15: 18 | F15: =D15*E15 | G15: =F15/12 | H15: =F15*'Rates'!$C$5*'Rates'!$C$8 | I15: Periodic monitoring
A16: Subtotal — DESIGN REACHBACK TEAM (18 months) | B16: =SUM(B6:B15) | D16: =SUM(D6:D15) | F16: =SUM(F6:F15) | G16: =SUM(G6:G15) | H16: =SUM(H6:H15)
A18: TOTAL | B18: =B16 | D18: =D16 | F18: =F16 | G18: =G16 | H18: =H16
